axe_selenium_python/__init__.py
axe_selenium_python/axe.py
axe_selenium_python/package-lock.json
axe_selenium_python/package.json
axe_selenium_python/node_modules/axe-core/axe.min.js
axe_selenium_python/tests/__init__.py
axe_selenium_python/tests/conftest.py
axe_selenium_python/tests/test_axe.py
axe_selenium_python/tests/test_page.html
axe_selenium_python/tests/requirements/flake8.txt
axe_selenium_python/tests/requirements/tests.txt
axe_selenium_python/tests/src/axe.min.js
rh_axe_selenium_python-21.5.19.2.dist-info/LICENSE.txt
rh_axe_selenium_python-21.5.19.2.dist-info/METADATA
rh_axe_selenium_python-21.5.19.2.dist-info/WHEEL
rh_axe_selenium_python-21.5.19.2.dist-info/top_level.txt
rh_axe_selenium_python-21.5.19.2.dist-info/RECORD
