Metadata-Version: 2.1
Name: rh-axe-selenium-python
Version: 21.5.19.2
Summary: Python library to integrate axe and selenium for web                 accessibility testing.
Home-page: http://github.com/RedHatQE/axe-selenium-python
Author: Kimberly Sereduck
Author-email: mshriver@redhat.com
License: Mozilla Public License 2.0 (MPL 2.0)
Keywords: axe-core selenium pytest-selenium accessibility automation mozilla
Platform: UNKNOWN
Requires-Dist: selenium (>=3.0.2)
Requires-Dist: pytest (>=3.0)
